[
  {
    "Name": "Project1 Team1",
    "Status": 0,
    "TeamId": 1
  },
  {
    "Name": "Project1 Team2",
    "Status": 0,
    "TeamId": 2
  },
  {
    "Name": "Project1 Team3",
    "Status": 0,
    "TeamId": 3
  },
  {
    "Name": "Project1 Team4",
    "Status": 0,
    "TeamId": 4
  },
  {
    "Name": "Project1 Team5",
    "Status": 0,
    "TeamId": 5
  },
  {
    "Name": "Project1 Team6",
    "Status": 0,
    "TeamId": 6
  },
  {
    "Name": "Project1 Team7",
    "Status": 0,
    "TeamId": 7
  },
  {
    "Name": "Project1 Team8",
    "Status": 0,
    "TeamId": 8
  },
  {
    "Name": "Project1 Team9",
    "Status": 0,
    "TeamId": 9
  },
  {
    "Name": "Project1 Team10",
    "Status": 0,
    "TeamId": 10
  },
  {
    "Name": "Project1 Team11",
    "Status": 0,
    "TeamId": 11
  },
  {
    "Name": "Project1 Team12",
    "Status": 0,
    "TeamId": 12
  },
  {
    "Name": "Project1 Team13",
    "Status": 0,
    "TeamId": 13
  },
  {
    "Name": "Project2 Team1",
    "Status": 1,
    "TeamId": 1
  },
  {
    "Name": "Project2 Team2",
    "Status": 2,
    "TeamId": 2
  },
  {
    "Name": "Project2 Team3",
    "Status": 1,
    "TeamId": 3
  },
  {
    "Name": "Project2 Team4",
    "Status": 1,
    "TeamId": 4
  },
  {
    "Name": "Project2 Team5",
    "Status": 1,
    "TeamId": 5
  },
  {
    "Name": "Project2 Team6",
    "Status": 1,
    "TeamId": 6
  },
  {
    "Name": "Project2 Team7",
    "Status": 1,
    "TeamId": 7
  },
  {
    "Name": "Project2 Team8",
    "Status": 1,
    "TeamId": 8
  },
  {
    "Name": "Project2 Team9",
    "Status": 1,
    "TeamId": 9
  },
  {
    "Name": "Project2 Team11",
    "Status": 1,
    "TeamId": 11
  },
  {
    "Name": "Project2 Team11",
    "Status": 1,
    "TeamId": 11
  },
  {
    "Name": "Project2 Team12",
    "Status": 1,
    "TeamId": 12
  },
  {
    "Name": "Project2 Team13",
    "Status": 1,
    "TeamId": 13
  },
  {
    "Name": "Project3 Team1",
    "Status": 0,
    "TeamId": 1
  },
  {
    "Name": "Project3 Team2",
    "Status": 0,
    "TeamId": 2
  },
  {
    "Name": "Project3 Team3",
    "Status": 0,
    "TeamId": 3
  },
  {
    "Name": "Project3 Team4",
    "Status": 0,
    "TeamId": 4
  },
  {
    "Name": "Project3 Team5",
    "Status": 0,
    "TeamId": 5
  },
  {
    "Name": "Project3 Team6",
    "Status": 0,
    "TeamId": 6
  },
  {
    "Name": "Project3 Team7",
    "Status": 0,
    "TeamId": 7
  },
  {
    "Name": "Project3 Team8",
    "Status": 0,
    "TeamId": 8
  },
  {
    "Name": "Project3 Team9",
    "Status": 0,
    "TeamId": 9
  },
  {
    "Name": "Project3 Team10",
    "Status": 0,
    "TeamId": 10
  },
  {
    "Name": "Project3 Team11",
    "Status": 0,
    "TeamId": 11
  },
  {
    "Name": "Project3 Team12",
    "Status": 0,
    "TeamId": 12
  },
  {
    "Name": "Project3 Team13",
    "Status": 0,
    "TeamId": 13
  }
]